foundry_cli/__init__.py
foundry_cli/main.py
foundry_ml_cli-0.0.1.dist-info/METADATA
foundry_ml_cli-0.0.1.dist-info/WHEEL
foundry_ml_cli-0.0.1.dist-info/entry_points.txt
foundry_ml_cli-0.0.1.dist-info/top_level.txt
foundry_ml_cli-0.0.1.dist-info/RECORD
