Metadata-Version: 2.1
Name: foundry-ml-cli
Version: 0.0.1
Summary: Foundry CLI
Home-page: https://github.com/MLMI2-CSSI/foundry-cli
Author: Ben Blaiszik
Author-email: blaiszik@uchicago.edu
License: UNKNOWN
Platform: UNKNOWN
Requires-Python: >=3.5
Requires-Dist: click
Requires-Dist: joblib
Requires-Dist: dlhub-sdk
Requires-Dist: foundry-ml
